kegbot_pycore2-1.2.3-nspkg.pth
kegbot/pycore/__init__.py
kegbot/pycore/backend.py
kegbot/pycore/common_defs.py
kegbot/pycore/flow.py
kegbot/pycore/flow_meter.py
kegbot/pycore/flow_meter_test.py
kegbot/pycore/flow_test.py
kegbot/pycore/kb_threads.py
kegbot/pycore/kbevent.py
kegbot/pycore/kegbot_app.py
kegbot/pycore/kegbot_test.py
kegbot/pycore/kegnet.py
kegbot/pycore/manager.py
kegbot/pycore/manager_test.py
kegbot/pycore/tap.py
kegbot/pycore/tap_test.py
kegbot_pycore2-1.2.3.data/scripts/kegboard_daemon.py
kegbot_pycore2-1.2.3.data/scripts/kegbot_core.py
kegbot_pycore2-1.2.3.data/scripts/lcd_daemon.py
kegbot_pycore2-1.2.3.data/scripts/rfid_daemon.py
kegbot_pycore2-1.2.3.data/scripts/test_flow.py
kegbot_pycore2-1.2.3.dist-info/DESCRIPTION.rst
kegbot_pycore2-1.2.3.dist-info/METADATA
kegbot_pycore2-1.2.3.dist-info/RECORD
kegbot_pycore2-1.2.3.dist-info/WHEEL
kegbot_pycore2-1.2.3.dist-info/metadata.json
kegbot_pycore2-1.2.3.dist-info/namespace_packages.txt
kegbot_pycore2-1.2.3.dist-info/top_level.txt
