Metadata-Version: 2.0
Name: kegbot-pycore2
Version: 1.2.3
Summary: Standalone Python Kegbot Core.
Home-page: https://kegbot.org/docs/pycore
Author: Bevbot LLC (updated by dandrzej80)
Author-email: info@bevbot.com
License: UNKNOWN
Platform: UNKNOWN
Requires-Dist: kegbot-api (>=0.1.17)
Requires-Dist: kegbot-kegboard2 (==1.1.5)
Requires-Dist: kegbot-pyutils (==0.1.7)
Requires-Dist: python-gflags (==2.0)
Requires-Dist: redis (<3.0,>=2.9.1)
